{
	"type": "minecraft:block",
	"pools": [
		{
			"name": "standard",
			"rolls": 1,
			"entries": [
				{
					"type": "minecraft:alternatives",
					"children": [
						{
							"type": "minecraft:item",
							"conditions": [
								{
									"condition": "minecraft:match_tool",
									"predicate": {
										"enchantments": [
											{
												"enchantment": "minecraft:silk_touch",
												"levels": {
													"min": 1
												}
											}
										]
									}
								}
							],
							"name": "iceandshadow3:polis_petrified_bricks"
						},
						{
							"type": "minecraft:item",
							"name": "iceandshadow3:polis_petrified_brick",
							"functions": [
								{
									"function": "minecraft:set_count",
									"count": 4
								},
								{
									"function": "minecraft:explosion_decay"
								}
							]
						}
					]
				}
			]
		}
	]
}
